str2int/__init__.py
str2int/strtoint.py
strtoint-0.0.1.dist-info/LICENSE
strtoint-0.0.1.dist-info/METADATA
strtoint-0.0.1.dist-info/WHEEL
strtoint-0.0.1.dist-info/top_level.txt
strtoint-0.0.1.dist-info/RECORD
