Metadata-Version: 2.1
Name: strtoint
Version: 0.0.1
Summary: .
Home-page: https://github.com/seoul2k/str2int
Author: xiongtianshuo
Author-email: Mr_Xiongts@163.com
Project-URL: Bug Tracker, https://github.com/seoul2k/str2int/issues
Classifier: Development Status :: 4 - Beta
Classifier: Operating System :: OS Independent
Classifier: Intended Audience :: Developers
Classifier: License :: OSI Approved :: BSD License
Classifier: Programming Language :: Python
Classifier: Programming Language :: Python :: Implementation
Classifier: Programming Language :: Python :: 3
Classifier: Programming Language :: Python :: 3.4
Classifier: Programming Language :: Python :: 3.5
Classifier: Programming Language :: Python :: 3.6
Classifier: Programming Language :: Python :: 3.8
Classifier: Topic :: Software Development :: Libraries
Requires-Python: >=2
License-File: LICENSE
Requires-Dist: pinyin2hanzi
Requires-Dist: pinyin
